{
  "id": "ordinance_sb_10_2020-1983",
  "type": "ordinance",
  "number": "2020-1983",
  "title": "Ordinance Amending Section 13 and Section 14 Subsection 14.1 of Municipal Ordinance No. 2015-1403 Dated January 19, 2015 Entitled \"an Ordinance Prescribing Guidelines and Policies on the Operation and Management of the Basic Emergency Obstetrics and the Newborn (bemonc) Facilities in the Municipality of Los Ba\u00f1os, Laguna and for Other Purposes.",
  "session_id": "sb_10_2020-02-24",
  "author_ids": [],
  "status": "active",
  "date_enacted": "2020-02-24",
  "link": "https://losbanos.gov.ph/public/storage/ordinances/Ordinance No. 2020-1983_1666231857.pdf",
  "subjects": []
}