{
  "id": "ordinance_sb_10_2021-2199",
  "type": "ordinance",
  "number": "2021-2199",
  "title": "Ordinance Approving the Annual Budget of Sangguniang Kabataan of Barangay Anos, Los Ba\u00f1os, Laguna for the Year 2021 in the Amount of Eight Hundred Sixty One Thousand Pesos and 00/100 Only. (P861,000.00) for Fiscal Year 2021.",
  "session_id": "sb_10_2021-10-20",
  "author_ids": [
    "ciceron-jerico"
  ],
  "status": "active",
  "date_enacted": "2021-10-20",
  "link": "https://losbanos.gov.ph/public/storage/ordinances/Ordinance No 2021-2199_1658455281.pdf",
  "subjects": []
}