{
  "id": "ordinance_sb_10_2022-2275",
  "type": "ordinance",
  "number": "2022-2275",
  "title": "Ordinance Enacting the Supplemental Budget in the Total Amount of Forty-two Million Two Hundred Ninety-seven Thousand Seven Hundred Fifty-four Pesos and 53/100 (P 42,297,754.53) Chargeable Against the Beginning Balance for Cy 2022.",
  "session_id": "sb_10_2022-02-08",
  "author_ids": [
    "ciceron-jerico"
  ],
  "status": "active",
  "date_enacted": "2022-02-08",
  "link": "https://losbanos.gov.ph/public/storage/ordinances/Ordinance No. 2022-2275_1657768205.pdf",
  "subjects": []
}