{
  "id": "resolution_sb_10_2020-92",
  "type": "resolution",
  "number": "2020-92",
  "title": "Resolution Approving and Adopting Municipal Development Council (MDC) Resolution No. 2020-03, Dated April 24, 2020, ?resolution Realigning a Portion of the Allocation for Construction / Rehabilitation / Improvement of Multi-purpose Halls Amounting to Three Hundred Ninety-five Thousand One Hundred Twenty-eight Pesos (PHP 395,128.00) Under the 20% Municipal Development Fund Cy 2020 Current Appropriations Thereafter Appropriating and Approving the Same for Various Projects. (author: Hon. Geronimo a",
  "session_id": "sb_10_2020-04-24",
  "author_ids": [
    "ciceron-jerico"
  ],
  "status": "active",
  "date_enacted": "2020-04-24",
  "link": "https://losbanos.gov.ph/public/storage/municipal_resolution/Resolution No. 2020-92 .pdf",
  "subjects": []
}