{
  "id": "resolution_sb_10_2020-28",
  "type": "resolution",
  "number": "2020-28",
  "title": "Resolution Approving the Renewal of Accreditation of Batong Malake Public Market Los Ba\u00f1os Tricycle Operators Drivers Association (BMPMLBTODA), Inc. with Office Address at Brgy. Batong Malake, Los Ba\u00f1os, Laguna. (AUTHOR: HON. JANOS S. LAPIZ, 01/31/20)",
  "session_id": "sb_10_2020-01-31",
  "author_ids": [
    "lapiz-janos-s"
  ],
  "status": "active",
  "date_enacted": "2020-01-31",
  "link": "https://losbanos.gov.ph/public/storage/municipal_resolution/Resolution No. 2020-28 .pdf",
  "subjects": []
}