{
  "id": "resolution_sb_10_2021-68",
  "type": "resolution",
  "number": "2021-68",
  "title": "Resolution Approving and Adopting the Municipal Disaster Risk Reduction and Management Council MDRRMC) 2021-07 Dated April 07, 2021 Entitled ? Resolution Realigning the Amount of One Million Six Hundred Forty Six Thousand Four Hundred Twenty Pesos ( P 1,646,420.00) From Various Projects and Activities Under the 5% Municipal Disaster Risk Reduction and Management Fund Current Appropriations for Damayan sa Kapwa Laban sa Covid-19 Rice Distribution and Further Approving the Same.? (author: Hon.",
  "session_id": "sb_10_2021-04-07",
  "author_ids": [],
  "status": "active",
  "date_enacted": "2021-04-07",
  "link": "https://losbanos.gov.ph/public/storage/municipal_resolution/Resolution No.  2021-68.pdf",
  "subjects": []
}