{
  "id": "resolution_sb_10_2020-224",
  "type": "resolution",
  "number": "2020-224",
  "title": "Resolution Approving and Adopting the Market Management Committee Resolution No. 2020-02 Dated December 16, 2020 ? Resolution Allowing the Holding of Baratillo at the Batong Malake Public Market and Poblacion Public Market on December 24, 25, 31. 2020 and January 1, 2021.? (AUTHOR : COUNCILOR MIKE DEXTER A. CONCIO, 12/21/2020)",
  "session_id": "sb_10_2020-12-21",
  "author_ids": [],
  "status": "active",
  "date_enacted": "2020-12-21",
  "link": "https://losbanos.gov.ph/public/storage/municipal_resolution/Resolution No. 2020-224.pdf",
  "subjects": []
}