{
  "id": "resolution_sb_10_2021-213",
  "type": "resolution",
  "number": "2021-213",
  "title": "Resolution Approving and Adopting Municipal Disaster Risk Reduction and Management Council 2021-15 Dated September 16, 2021 Entitled: ? Resolution Approving the Adjusted Municipal Disaster Risk Reduction and Management Plan and Fund for Cy 2022 Amounting to Twenty-one Million Eight Hundred Thirty-two Thousand Four Hundred Eighty-two Pesos and Sixty-three Centavos (php21,832,482.63).? (AUTHOR: COUNCILOR JANOS S. LAPIZ, 10/04/2021)",
  "session_id": "sb_10_2021-10-04",
  "author_ids": [],
  "status": "active",
  "date_enacted": "2021-10-04",
  "link": "https://losbanos.gov.ph/public/storage/municipal_resolution/Resolution No.  2021-213.pdf",
  "subjects": []
}