{
  "id": "executive_order_sb_10_2021-030",
  "type": "executive_order",
  "number": "2021-030",
  "title": "Directing the Reorganization of the Construction Permitting Task Force for the Streamlining of the Process for the Issuance of Building Permits and Certificate Occupancy (BPCO) in the Municipality of Los Ba\u00f1os.",
  "session_id": "sb_10_2021-05-19",
  "author_ids": [],
  "status": "active",
  "date_enacted": "2021-05-19",
  "link": "https://losbanos.gov.ph/public/storage/executive_orders/EO-2021-030_1629437678.pdf",
  "subjects": []
}