{
  "id": "executive_order_sb_10_2021-021",
  "type": "executive_order",
  "number": "2021-021",
  "title": "An Order Reducing Hours of Work Transactions in the Municipal Government of Los Ba\u00f1os from Eight O'Clock in the Morning (8:00 AM) to Two O'Clock in the afternoon (2:00 PM), Monday to Friday.",
  "session_id": "sb_10_2021-03-23",
  "author_ids": [],
  "status": "active",
  "date_enacted": "2021-03-23",
  "link": "https://losbanos.gov.ph/public/storage/executive_orders/EO-2021-021_1629098135.pdf",
  "subjects": []
}