{
  "id": "resolution_legacy_kapasiyahan-blg-2022-71",
  "type": "resolution",
  "number": "KAPASIYAHAN BLG. 2022-71",
  "title": "Kapasiyahang Pinagtitibay Ang Kautusang Pambarangay Blg. 23-s-2022 ng Sangguniang Barangay ng Bambang: ?kautusang Pambarangay Na Nagbabawal sa Sinumang Tao Na Mag-utos, sa Isang Menor De Edad Na Bata Na Bumili ng Alak, Sigarilyo, At/o Anumang Uri ng Tabako at Pamalit Dito Gaya ng Vape at mga Katulad Na Produkto sa mga Tindahan sa Barangay Bambang, Pagtatadhana ng Panuntunan ng Pagpapatupad at mga Kaukulang Parusa sa Sinumang Lalabag Dito, at Para sa Iba Pang Layunin?. (author:councilor Arlene P.",
  "session_id": "",
  "author_ids": [],
  "status": "active",
  "date_enacted": "",
  "link": "https://losbanos.gov.ph/public/storage/municipal_resolution/Resolution No. 2022-71 (2).pdf",
  "subjects": []
}